{
  "annotations": {
    "list": [
      {
        "builtIn": 1,
        "datasource": {
          "type": "grafana",
          "uid": "-- Grafana --"
        },
        "enable": true,
        "hide": true,
        "iconColor": "rgba(0, 211, 255, 1)",
        "name": "Annotations & Alerts",
        "type": "dashboard"
      }
    ]
  },
  "editable": true,
  "fiscalYearStartMonth": 0,
  "graphTooltip": 1,
  "id": 20,
  "links": [],
  "panels": [
    {
      "datasource": {
        "type": "prometheus",
        "uid": "afdnigtrjrhfke"
      },
      "fieldConfig": {
        "defaults": {
          "color": {
            "mode": "thresholds"
          },
          "mappings": [],
          "thresholds": {
            "mode": "absolute",
            "steps": [
              {
                "color": "green",
                "value": 0
              }
            ]
          },
          "unit": "s"
        },
        "overrides": []
      },
      "gridPos": {
        "h": 4,
        "w": 4,
        "x": 0,
        "y": 0
      },
      "id": 1,
      "options": {
        "colorMode": "background",
        "graphMode": "none",
        "justifyMode": "auto",
        "orientation": "auto",
        "percentChangeColorMode": "standard",
        "reduceOptions": {
          "calcs": [
            "lastNotNull"
          ],
          "fields": "",
          "values": false
        },
        "showPercentChange": false,
        "textMode": "auto",
        "wideLayout": true
      },
      "pluginVersion": "12.3.0",
      "targets": [
        {
          "datasource": {
            "type": "prometheus",
            "uid": "afdnigtrjrhfke"
          },
          "expr": "sysUpTime{job=\"mikrotik-router\"} / 100",
          "instant": true,
          "legendFormat": "Uptime",
          "refId": "A"
        }
      ],
      "title": "Router Uptime",
      "type": "stat"
    },
    {
      "datasource": {
        "type": "prometheus",
        "uid": "afdnigtrjrhfke"
      },
      "fieldConfig": {
        "defaults": {
          "color": {
            "mode": "thresholds"
          },
          "mappings": [],
          "max": 100,
          "min": 0,
          "thresholds": {
            "mode": "absolute",
            "steps": [
              {
                "color": "green",
                "value": 0
              },
              {
                "color": "yellow",
                "value": 50
              },
              {
                "color": "red",
                "value": 80
              }
            ]
          },
          "unit": "percent"
        },
        "overrides": []
      },
      "gridPos": {
        "h": 4,
        "w": 4,
        "x": 4,
        "y": 0
      },
      "id": 2,
      "options": {
        "colorMode": "background",
        "graphMode": "none",
        "justifyMode": "auto",
        "orientation": "auto",
        "percentChangeColorMode": "standard",
        "reduceOptions": {
          "calcs": [
            "lastNotNull"
          ],
          "fields": "",
          "values": false
        },
        "showPercentChange": false,
        "textMode": "auto",
        "wideLayout": true
      },
      "pluginVersion": "12.3.0",
      "targets": [
        {
          "datasource": {
            "type": "prometheus",
            "uid": "afdnigtrjrhfke"
          },
          "expr": "mtxrCPULoad{job=\"mikrotik-router\"} / 10",
          "instant": true,
          "legendFormat": "CPU %",
          "refId": "A"
        }
      ],
      "title": "CPU Load",
      "type": "stat"
    },
    {
      "datasource": {
        "type": "prometheus",
        "uid": "afdnigtrjrhfke"
      },
      "fieldConfig": {
        "defaults": {
          "color": {
            "mode": "thresholds"
          },
          "mappings": [],
          "max": 100,
          "min": 0,
          "thresholds": {
            "mode": "absolute",
            "steps": [
              {
                "color": "green",
                "value": 0
              },
              {
                "color": "yellow",
                "value": 70
              },
              {
                "color": "red",
                "value": 90
              }
            ]
          },
          "unit": "percent"
        },
        "overrides": []
      },
      "gridPos": {
        "h": 4,
        "w": 4,
        "x": 8,
        "y": 0
      },
      "id": 3,
      "options": {
        "colorMode": "background",
        "graphMode": "none",
        "justifyMode": "auto",
        "orientation": "auto",
        "percentChangeColorMode": "standard",
        "reduceOptions": {
          "calcs": [
            "lastNotNull"
          ],
          "fields": "",
          "values": false
        },
        "showPercentChange": false,
        "textMode": "auto",
        "wideLayout": true
      },
      "pluginVersion": "12.3.0",
      "targets": [
        {
          "datasource": {
            "type": "prometheus",
            "uid": "afdnigtrjrhfke"
          },
          "expr": "100 * hrStorageUsed{job=\"mikrotik-router\", hrStorageDescr=\"main memory\"} / hrStorageSize{job=\"mikrotik-router\", hrStorageDescr=\"main memory\"}",
          "instant": true,
          "legendFormat": "RAM %",
          "refId": "A"
        }
      ],
      "title": "Memory Used",
      "type": "stat"
    },
    {
      "datasource": {
        "type": "prometheus",
        "uid": "afdnigtrjrhfke"
      },
      "fieldConfig": {
        "defaults": {
          "color": {
            "mode": "thresholds"
          },
          "mappings": [],
          "max": 100,
          "min": 0,
          "thresholds": {
            "mode": "absolute",
            "steps": [
              {
                "color": "green",
                "value": 0
              },
              {
                "color": "yellow",
                "value": 70
              },
              {
                "color": "red",
                "value": 90
              }
            ]
          },
          "unit": "percent"
        },
        "overrides": []
      },
      "gridPos": {
        "h": 4,
        "w": 4,
        "x": 12,
        "y": 0
      },
      "id": 4,
      "options": {
        "colorMode": "background",
        "graphMode": "none",
        "justifyMode": "auto",
        "orientation": "auto",
        "percentChangeColorMode": "standard",
        "reduceOptions": {
          "calcs": [
            "lastNotNull"
          ],
          "fields": "",
          "values": false
        },
        "showPercentChange": false,
        "textMode": "auto",
        "wideLayout": true
      },
      "pluginVersion": "12.3.0",
      "targets": [
        {
          "datasource": {
            "type": "prometheus",
            "uid": "afdnigtrjrhfke"
          },
          "expr": "100 * hrStorageUsed{job=\"mikrotik-router\", hrStorageDescr=\"system disk\"} / hrStorageSize{job=\"mikrotik-router\", hrStorageDescr=\"system disk\"}",
          "instant": true,
          "legendFormat": "Disk %",
          "refId": "A"
        }
      ],
      "title": "Disk Used",
      "type": "stat"
    },
    {
      "datasource": {
        "type": "prometheus",
        "uid": "afdnigtrjrhfke"
      },
      "fieldConfig": {
        "defaults": {
          "color": {
            "mode": "thresholds"
          },
          "mappings": [],
          "thresholds": {
            "mode": "absolute",
            "steps": [
              {
                "color": "green",
                "value": 0
              }
            ]
          },
          "unit": "short"
        },
        "overrides": []
      },
      "gridPos": {
        "h": 4,
        "w": 4,
        "x": 16,
        "y": 0
      },
      "id": 5,
      "options": {
        "colorMode": "background",
        "graphMode": "none",
        "justifyMode": "auto",
        "orientation": "auto",
        "percentChangeColorMode": "standard",
        "reduceOptions": {
          "calcs": [
            "lastNotNull"
          ],
          "fields": "",
          "values": false
        },
        "showPercentChange": false,
        "textMode": "auto",
        "wideLayout": true
      },
      "pluginVersion": "12.3.0",
      "targets": [
        {
          "datasource": {
            "type": "prometheus",
            "uid": "afdnigtrjrhfke"
          },
          "expr": "count(ifOperStatus{job=\"mikrotik-router\"} == 1)",
          "instant": true,
          "legendFormat": "UP",
          "refId": "A"
        }
      ],
      "title": "Active Interfaces",
      "type": "stat"
    },
    {
      "datasource": {
        "type": "prometheus",
        "uid": "afdnigtrjrhfke"
      },
      "fieldConfig": {
        "defaults": {
          "color": {
            "mode": "thresholds"
          },
          "mappings": [],
          "thresholds": {
            "mode": "absolute",
            "steps": [
              {
                "color": "blue",
                "value": 0
              }
            ]
          },
          "unit": "bps"
        },
        "overrides": []
      },
      "gridPos": {
        "h": 4,
        "w": 4,
        "x": 20,
        "y": 0
      },
      "id": 6,
      "options": {
        "colorMode": "background",
        "graphMode": "none",
        "justifyMode": "auto",
        "orientation": "auto",
        "percentChangeColorMode": "standard",
        "reduceOptions": {
          "calcs": [
            "lastNotNull"
          ],
          "fields": "",
          "values": false
        },
        "showPercentChange": false,
        "textMode": "auto",
        "wideLayout": true
      },
      "pluginVersion": "12.3.0",
      "targets": [
        {
          "datasource": {
            "type": "prometheus",
            "uid": "afdnigtrjrhfke"
          },
          "expr": "rate(ifHCInOctets{job=\"mikrotik-router\", ifDescr=\"pppoe-out848\"}[5m]) * 8",
          "instant": true,
          "legendFormat": "PPPoE Down",
          "refId": "A"
        }
      ],
      "title": "PPPoE Download Speed",
      "type": "stat"
    },
    {
      "datasource": {
        "type": "prometheus",
        "uid": "afdnigtrjrhfke"
      },
      "fieldConfig": {
        "defaults": {
          "color": {
            "mode": "palette-classic"
          },
          "custom": {
            "axisBorderShow": false,
            "axisCenteredZero": false,
            "axisColorMode": "text",
            "axisLabel": "",
            "axisPlacement": "auto",
            "barAlignment": 0,
            "barWidthFactor": 0.6,
            "drawStyle": "line",
            "fillOpacity": 10,
            "gradientMode": "none",
            "hideFrom": {
              "legend": false,
              "tooltip": false,
              "viz": false
            },
            "insertNulls": false,
            "lineInterpolation": "linear",
            "lineWidth": 2,
            "pointSize": 5,
            "scaleDistribution": {
              "type": "linear"
            },
            "showPoints": "auto",
            "showValues": false,
            "spanNulls": false,
            "stacking": {
              "group": "A",
              "mode": "none"
            },
            "thresholdsStyle": {
              "mode": "off"
            }
          },
          "mappings": [],
          "thresholds": {
            "mode": "absolute",
            "steps": [
              {
                "color": "green",
                "value": 0
              },
              {
                "color": "red",
                "value": 80
              }
            ]
          },
          "unit": "bps"
        },
        "overrides": [
          {
            "matcher": {
              "id": "byName",
              "options": "Download"
            },
            "properties": [
              {
                "id": "color",
                "value": {
                  "fixedColor": "green",
                  "mode": "fixed"
                }
              }
            ]
          },
          {
            "matcher": {
              "id": "byName",
              "options": "Upload"
            },
            "properties": [
              {
                "id": "color",
                "value": {
                  "fixedColor": "orange",
                  "mode": "fixed"
                }
              }
            ]
          }
        ]
      },
      "gridPos": {
        "h": 8,
        "w": 12,
        "x": 0,
        "y": 4
      },
      "id": 7,
      "options": {
        "legend": {
          "calcs": [],
          "displayMode": "list",
          "placement": "bottom",
          "showLegend": true
        },
        "tooltip": {
          "hideZeros": false,
          "mode": "multi",
          "sort": "none"
        }
      },
      "pluginVersion": "12.3.0",
      "targets": [
        {
          "datasource": {
            "type": "prometheus",
            "uid": "afdnigtrjrhfke"
          },
          "expr": "rate(ifHCInOctets{job=\"mikrotik-router\", ifDescr=\"pppoe-out848\"}[5m]) * 8",
          "legendFormat": "Download",
          "refId": "A"
        },
        {
          "datasource": {
            "type": "prometheus",
            "uid": "afdnigtrjrhfke"
          },
          "expr": "rate(ifHCOutOctets{job=\"mikrotik-router\", ifDescr=\"pppoe-out848\"}[5m]) * 8",
          "legendFormat": "Upload",
          "refId": "B"
        }
      ],
      "title": "WAN Traffic (pppoe-out848)",
      "type": "timeseries"
    },
    {
      "datasource": {
        "type": "prometheus",
        "uid": "afdnigtrjrhfke"
      },
      "fieldConfig": {
        "defaults": {
          "color": {
            "mode": "palette-classic"
          },
          "custom": {
            "axisBorderShow": false,
            "axisCenteredZero": false,
            "axisColorMode": "text",
            "axisLabel": "",
            "axisPlacement": "auto",
            "barAlignment": 0,
            "barWidthFactor": 0.6,
            "drawStyle": "line",
            "fillOpacity": 10,
            "gradientMode": "none",
            "hideFrom": {
              "legend": false,
              "tooltip": false,
              "viz": false
            },
            "insertNulls": false,
            "lineInterpolation": "linear",
            "lineWidth": 2,
            "pointSize": 5,
            "scaleDistribution": {
              "type": "linear"
            },
            "showPoints": "auto",
            "showValues": false,
            "spanNulls": false,
            "stacking": {
              "group": "A",
              "mode": "none"
            },
            "thresholdsStyle": {
              "mode": "off"
            }
          },
          "mappings": [],
          "thresholds": {
            "mode": "absolute",
            "steps": [
              {
                "color": "green",
                "value": 0
              },
              {
                "color": "red",
                "value": 80
              }
            ]
          },
          "unit": "bps"
        },
        "overrides": [
          {
            "matcher": {
              "id": "byName",
              "options": "In"
            },
            "properties": [
              {
                "id": "color",
                "value": {
                  "fixedColor": "green",
                  "mode": "fixed"
                }
              }
            ]
          },
          {
            "matcher": {
              "id": "byName",
              "options": "Out"
            },
            "properties": [
              {
                "id": "color",
                "value": {
                  "fixedColor": "blue",
                  "mode": "fixed"
                }
              }
            ]
          }
        ]
      },
      "gridPos": {
        "h": 8,
        "w": 12,
        "x": 12,
        "y": 4
      },
      "id": 8,
      "options": {
        "legend": {
          "calcs": [],
          "displayMode": "list",
          "placement": "bottom",
          "showLegend": true
        },
        "tooltip": {
          "hideZeros": false,
          "mode": "multi",
          "sort": "none"
        }
      },
      "pluginVersion": "12.3.0",
      "targets": [
        {
          "datasource": {
            "type": "prometheus",
            "uid": "afdnigtrjrhfke"
          },
          "expr": "rate(ifHCInOctets{job=\"mikrotik-router\", ifDescr=\"bridge-default\"}[5m]) * 8",
          "legendFormat": "In",
          "refId": "A"
        },
        {
          "datasource": {
            "type": "prometheus",
            "uid": "afdnigtrjrhfke"
          },
          "expr": "rate(ifHCOutOctets{job=\"mikrotik-router\", ifDescr=\"bridge-default\"}[5m]) * 8",
          "legendFormat": "Out",
          "refId": "B"
        }
      ],
      "title": "LAN Traffic (bridge-default)",
      "type": "timeseries"
    },
    {
      "datasource": {
        "type": "prometheus",
        "uid": "afdnigtrjrhfke"
      },
      "fieldConfig": {
        "defaults": {
          "color": {
            "fixedColor": "red",
            "mode": "fixed"
          },
          "custom": {
            "axisBorderShow": false,
            "axisCenteredZero": false,
            "axisColorMode": "text",
            "axisLabel": "",
            "axisPlacement": "auto",
            "barAlignment": 0,
            "barWidthFactor": 0.6,
            "drawStyle": "line",
            "fillOpacity": 20,
            "gradientMode": "none",
            "hideFrom": {
              "legend": false,
              "tooltip": false,
              "viz": false
            },
            "insertNulls": false,
            "lineInterpolation": "linear",
            "lineWidth": 2,
            "pointSize": 5,
            "scaleDistribution": {
              "type": "linear"
            },
            "showPoints": "auto",
            "showValues": false,
            "spanNulls": false,
            "stacking": {
              "group": "A",
              "mode": "none"
            },
            "thresholdsStyle": {
              "mode": "off"
            }
          },
          "mappings": [],
          "max": 100,
          "min": 0,
          "thresholds": {
            "mode": "absolute",
            "steps": [
              {
                "color": "green",
                "value": 0
              },
              {
                "color": "red",
                "value": 80
              }
            ]
          },
          "unit": "percent"
        },
        "overrides": []
      },
      "gridPos": {
        "h": 8,
        "w": 12,
        "x": 0,
        "y": 12
      },
      "id": 9,
      "options": {
        "legend": {
          "calcs": [],
          "displayMode": "list",
          "placement": "bottom",
          "showLegend": true
        },
        "tooltip": {
          "hideZeros": false,
          "mode": "single",
          "sort": "none"
        }
      },
      "pluginVersion": "12.3.0",
      "targets": [
        {
          "datasource": {
            "type": "prometheus",
            "uid": "afdnigtrjrhfke"
          },
          "expr": "mtxrCPULoad{job=\"mikrotik-router\"} / 10",
          "legendFormat": "CPU %",
          "refId": "A"
        }
      ],
      "title": "CPU Load Over Time",
      "type": "timeseries"
    },
    {
      "datasource": {
        "type": "prometheus",
        "uid": "afdnigtrjrhfke"
      },
      "fieldConfig": {
        "defaults": {
          "color": {
            "fixedColor": "purple",
            "mode": "fixed"
          },
          "custom": {
            "axisBorderShow": false,
            "axisCenteredZero": false,
            "axisColorMode": "text",
            "axisLabel": "",
            "axisPlacement": "auto",
            "barAlignment": 0,
            "barWidthFactor": 0.6,
            "drawStyle": "line",
            "fillOpacity": 20,
            "gradientMode": "none",
            "hideFrom": {
              "legend": false,
              "tooltip": false,
              "viz": false
            },
            "insertNulls": false,
            "lineInterpolation": "linear",
            "lineWidth": 2,
            "pointSize": 5,
            "scaleDistribution": {
              "type": "linear"
            },
            "showPoints": "auto",
            "showValues": false,
            "spanNulls": false,
            "stacking": {
              "group": "A",
              "mode": "none"
            },
            "thresholdsStyle": {
              "mode": "off"
            }
          },
          "mappings": [],
          "max": 100,
          "min": 0,
          "thresholds": {
            "mode": "absolute",
            "steps": [
              {
                "color": "green",
                "value": 0
              },
              {
                "color": "red",
                "value": 80
              }
            ]
          },
          "unit": "percent"
        },
        "overrides": []
      },
      "gridPos": {
        "h": 8,
        "w": 12,
        "x": 12,
        "y": 12
      },
      "id": 10,
      "options": {
        "legend": {
          "calcs": [],
          "displayMode": "list",
          "placement": "bottom",
          "showLegend": true
        },
        "tooltip": {
          "hideZeros": false,
          "mode": "single",
          "sort": "none"
        }
      },
      "pluginVersion": "12.3.0",
      "targets": [
        {
          "datasource": {
            "type": "prometheus",
            "uid": "afdnigtrjrhfke"
          },
          "expr": "100 * hrStorageUsed{job=\"mikrotik-router\", hrStorageDescr=\"main memory\"} / hrStorageSize{job=\"mikrotik-router\", hrStorageDescr=\"main memory\"}",
          "legendFormat": "RAM %",
          "refId": "A"
        }
      ],
      "title": "Memory Usage Over Time",
      "type": "timeseries"
    },
    {
      "datasource": {
        "type": "prometheus",
        "uid": "afdnigtrjrhfke"
      },
      "fieldConfig": {
        "defaults": {
          "color": {
            "mode": "palette-classic"
          },
          "custom": {
            "axisBorderShow": false,
            "axisCenteredZero": false,
            "axisColorMode": "text",
            "axisLabel": "",
            "axisPlacement": "auto",
            "barAlignment": 0,
            "barWidthFactor": 0.6,
            "drawStyle": "line",
            "fillOpacity": 5,
            "gradientMode": "none",
            "hideFrom": {
              "legend": false,
              "tooltip": false,
              "viz": false
            },
            "insertNulls": false,
            "lineInterpolation": "linear",
            "lineWidth": 1,
            "pointSize": 5,
            "scaleDistribution": {
              "type": "linear"
            },
            "showPoints": "auto",
            "showValues": false,
            "spanNulls": false,
            "stacking": {
              "group": "A",
              "mode": "none"
            },
            "thresholdsStyle": {
              "mode": "off"
            }
          },
          "mappings": [],
          "thresholds": {
            "mode": "absolute",
            "steps": [
              {
                "color": "green",
                "value": 0
              },
              {
                "color": "red",
                "value": 80
              }
            ]
          },
          "unit": "bps"
        },
        "overrides": [
          {
            "__systemRef": "hideSeriesFrom",
            "matcher": {
              "id": "byNames",
              "options": {
                "mode": "exclude",
                "names": [
                  "↓ Vlan100"
                ],
                "prefix": "All except:",
                "readOnly": true
              }
            },
            "properties": [
              {
                "id": "custom.hideFrom",
                "value": {
                  "legend": false,
                  "tooltip": true,
                  "viz": true
                }
              }
            ]
          }
        ]
      },
      "gridPos": {
        "h": 8,
        "w": 24,
        "x": 0,
        "y": 20
      },
      "id": 11,
      "options": {
        "legend": {
          "calcs": [
            "mean",
            "max"
          ],
          "displayMode": "table",
          "placement": "right",
          "showLegend": true
        },
        "tooltip": {
          "hideZeros": false,
          "mode": "multi",
          "sort": "none"
        }
      },
      "pluginVersion": "12.3.0",
      "targets": [
        {
          "datasource": {
            "type": "prometheus",
            "uid": "afdnigtrjrhfke"
          },
          "expr": "rate(ifHCInOctets{job=\"mikrotik-router\", ifDescr=~\"Vlan.*\"}[5m]) * 8",
          "legendFormat": "↓ {{ifDescr}}",
          "refId": "A"
        },
        {
          "datasource": {
            "type": "prometheus",
            "uid": "afdnigtrjrhfke"
          },
          "expr": "rate(ifHCOutOctets{job=\"mikrotik-router\", ifDescr=~\"Vlan.*\"}[5m]) * 8",
          "legendFormat": "↑ {{ifDescr}}",
          "refId": "B"
        }
      ],
      "title": "VLAN Traffic",
      "type": "timeseries"
    },
    {
      "datasource": {
        "type": "prometheus",
        "uid": "afdnigtrjrhfke"
      },
      "fieldConfig": {
        "defaults": {
          "custom": {
            "align": "auto",
            "cellOptions": {
              "type": "auto"
            },
            "footer": {
              "reducers": []
            },
            "inspect": false
          },
          "mappings": [],
          "thresholds": {
            "mode": "absolute",
            "steps": [
              {
                "color": "green",
                "value": 0
              },
              {
                "color": "red",
                "value": 80
              }
            ]
          }
        },
        "overrides": [
          {
            "matcher": {
              "id": "byName",
              "options": "Value"
            },
            "properties": [
              {
                "id": "mappings",
                "value": [
                  {
                    "options": {
                      "1": {
                        "color": "green",
                        "text": "UP"
                      }
                    },
                    "type": "value"
                  },
                  {
                    "options": {
                      "2": {
                        "color": "red",
                        "text": "DOWN"
                      }
                    },
                    "type": "value"
                  }
                ]
              }
            ]
          }
        ]
      },
      "gridPos": {
        "h": 11,
        "w": 24,
        "x": 0,
        "y": 28
      },
      "id": 12,
      "options": {
        "cellHeight": "sm",
        "showHeader": true,
        "sortBy": [
          {
            "desc": false,
            "displayName": "Interface"
          }
        ]
      },
      "pluginVersion": "12.3.0",
      "targets": [
        {
          "datasource": {
            "type": "prometheus",
            "uid": "afdnigtrjrhfke"
          },
          "expr": "ifOperStatus{job=\"mikrotik-router\"}",
          "format": "table",
          "instant": true,
          "legendFormat": "{{ifDescr}}",
          "refId": "A"
        }
      ],
      "title": "Interface Status",
      "transformations": [
        {
          "id": "organize",
          "options": {
            "renameByName": {
              "Value": "Status",
              "ifDescr": "Interface"
            }
          }
        }
      ],
      "type": "table"
    },
    {
      "datasource": {
        "type": "prometheus",
        "uid": "afdnigtrjrhfke"
      },
      "fieldConfig": {
        "defaults": {
          "color": {
            "mode": "palette-classic"
          },
          "custom": {
            "axisBorderShow": false,
            "axisCenteredZero": false,
            "axisColorMode": "text",
            "axisLabel": "",
            "axisPlacement": "auto",
            "barAlignment": 0,
            "barWidthFactor": 0.6,
            "drawStyle": "line",
            "fillOpacity": 10,
            "gradientMode": "none",
            "hideFrom": {
              "legend": false,
              "tooltip": false,
              "viz": false
            },
            "insertNulls": false,
            "lineInterpolation": "linear",
            "lineWidth": 2,
            "pointSize": 5,
            "scaleDistribution": {
              "type": "linear"
            },
            "showPoints": "auto",
            "showValues": false,
            "spanNulls": false,
            "stacking": {
              "group": "A",
              "mode": "none"
            },
            "thresholdsStyle": {
              "mode": "off"
            }
          },
          "mappings": [],
          "thresholds": {
            "mode": "absolute",
            "steps": [
              {
                "color": "green",
                "value": 0
              },
              {
                "color": "red",
                "value": 80
              }
            ]
          },
          "unit": "bps"
        },
        "overrides": []
      },
      "gridPos": {
        "h": 7,
        "w": 24,
        "x": 0,
        "y": 39
      },
      "id": 13,
      "options": {
        "legend": {
          "calcs": [],
          "displayMode": "list",
          "placement": "bottom",
          "showLegend": true
        },
        "tooltip": {
          "hideZeros": false,
          "mode": "multi",
          "sort": "none"
        }
      },
      "pluginVersion": "12.3.0",
      "targets": [
        {
          "datasource": {
            "type": "prometheus",
            "uid": "afdnigtrjrhfke"
          },
          "expr": "rate(ifHCInOctets{job=\"mikrotik-router\", ifDescr=\"wireguard-vpn\"}[5m]) * 8",
          "legendFormat": "VPN Download",
          "refId": "A"
        },
        {
          "datasource": {
            "type": "prometheus",
            "uid": "afdnigtrjrhfke"
          },
          "expr": "rate(ifHCOutOctets{job=\"mikrotik-router\", ifDescr=\"wireguard-vpn\"}[5m]) * 8",
          "legendFormat": "VPN Upload",
          "refId": "B"
        }
      ],
      "title": "WireGuard VPN Traffic",
      "type": "timeseries"
    }
  ],
  "preload": false,
  "refresh": "30s",
  "schemaVersion": 42,
  "tags": [
    "mikrotik",
    "RB760iGS",
    "snmp exporter",
    "router"
  ],
  "templating": {
    "list": []
  },
  "time": {
    "from": "now-1h",
    "to": "now"
  },
  "timepicker": {},
  "timezone": "browser",
  "title": "MikroTik-Router Overview",
  "uid": "mikrotik-router-001",
  "version": 8
}
